fkutils_lib/__init__.py
fkutils_lib/string_handler.py
fkutils_lib-4.0.0.dist-info/METADATA
fkutils_lib-4.0.0.dist-info/WHEEL
fkutils_lib-4.0.0.dist-info/RECORD
