Metadata-Version: 2.1
Name: fkutils_lib
Version: 4.0.0
Summary: 
Author: rrzavan
Author-email: rrzavan@fkgrupo.com
Requires-Python: >=3.12,<4.0
Classifier: Programming Language :: Python :: 3
Classifier: Programming Language :: Python :: 3.12
Requires-Dist: poetry-bumpversion (>=0.3.2,<0.4.0)
